{
  "name": "MSc Financial Engineering",
  "url": "https://www.ntu.edu.sg/business/admissions/graduate-studies/msc-financial-engineering",
  "title": "",
  "description": "A unique graduate programme, the Master of Science (MSc) in Financial Engineering (MFE) at Nanyang Business School empowers you to succeed as a dynamic professional in the world of high technology finance. ​\nLearn from world class faculty and industry seasoned professionals how to im​plement solutions in areas such as risk management, product structuring, quantitative trading, quantitative research, and financial information technology.\nThis one-year programme is rigorous and intense and it is designed for those with a strong drive and focus to penetrate the top tiers of the finance industry. The curriculum emphasises teamwork and communication in real-life corporate settings, seamlessly\n integrating current financial theory and computational methods with practical knowledge.\nYou will get opportunities to learn from experts from a diversity of disciplines, spanning finance, computing, and mathematics. Close interaction with both faculty and industry professionals will enable you to amalgamate real-life experience with academic\n research to enrich your understanding of today’s financial world.\nStay ahead of industry developments in this multi disciplinary programme that is offered in collaboration with Carnegie Mellon University (CMU), USA. Non-CMU track is also available where you complete the programme in NTU.\nThe MSc Financial Engineering (MFE) programme at Nanyang Business School (NBS) aims to equip you with concepts and techniques in finance, computer science, and mathematics. You will learn how to apply sophisticated engineering tools to financial problems, utilising complex analytical and quantitative methods to tackle challenging problems in high-technology finance.\nHighlights of our MFE programme:\nOpportunity to spend a seven-week term at Carnegie Mellon University, USA\nExpertise from two NTU schools - NBS and School of Physical and Mathematical Sciences (SPMS)\nWorld class faculty\nInsights from industry professionals\nStrong alumni network\nAdmissions Outreach",
  "sections": {
    "南洋-交大EMBA | 一月说明会": "31 Jan 2026 02.30 PM - 03.15 PM 上海交通大学徐汇校区安泰楼A305 / 腾讯会议 Add to Calendar"
  },
  "degree_type": "MSc",
  "requirements": {}
}